uiwiz/__init__.py
uiwiz/app.py
uiwiz/element.py
uiwiz/element_types.py
uiwiz/event.py
uiwiz/frame.py
uiwiz/login_response.py
uiwiz/page_definition.py
uiwiz/page_route.py
uiwiz/shared.py
uiwiz/ui.py
uiwiz/version.py
uiwiz/docs/layout.py
uiwiz/docs/main.py
uiwiz/docs/page_docs.py
uiwiz/docs/pages/index.md
uiwiz/docs/pages/docs/elements.py
uiwiz/docs/pages/docs/extract_doc.py
uiwiz/elements/__init__.py
uiwiz/elements/avatar.py
uiwiz/elements/button.py
uiwiz/elements/checkbox.py
uiwiz/elements/col.py
uiwiz/elements/container.py
uiwiz/elements/datepicker.py
uiwiz/elements/divider.py
uiwiz/elements/drawer.py
uiwiz/elements/dropdown.py
uiwiz/elements/footer.py
uiwiz/elements/form.py
uiwiz/elements/full_width.py
uiwiz/elements/hidden_input.py
uiwiz/elements/html.py
uiwiz/elements/input.py
uiwiz/elements/label.py
uiwiz/elements/link.py
uiwiz/elements/nav.py
uiwiz/elements/number.py
uiwiz/elements/radio.py
uiwiz/elements/range.py
uiwiz/elements/row.py
uiwiz/elements/spinner.py
uiwiz/elements/table.py
uiwiz/elements/tabs.py
uiwiz/elements/textarea.py
uiwiz/elements/theme_selector.py
uiwiz/elements/toast.py
uiwiz/elements/toggle.py
uiwiz/elements/upload.py
uiwiz/elements/ace/LICENSE
uiwiz/elements/ace/__init__.py
uiwiz/elements/ace/ace-lang-tool.min.js
uiwiz/elements/ace/ace.js
uiwiz/elements/ace/ace.min.js
uiwiz/elements/ace/ace.py
uiwiz/elements/ace/ace_options.py
uiwiz/elements/ace/acetheme.css
uiwiz/elements/ace/mode-python.js
uiwiz/elements/ace/mode-sql.js
uiwiz/elements/ace/snippets/python.js
uiwiz/elements/ace/snippets/sql.js
uiwiz/elements/aggrid/LICENSE
uiwiz/elements/aggrid/aggrid-community.min.js
uiwiz/elements/aggrid/aggrid.js
uiwiz/elements/aggrid/aggrid.py
uiwiz/elements/aggrid/aggridtheme.css
uiwiz/elements/dict/copy.js
uiwiz/elements/dict/dict.py
uiwiz/elements/echart/LICENSE
uiwiz/elements/echart/echart.js
uiwiz/elements/echart/echart.min.js
uiwiz/elements/echart/echart.py
uiwiz/elements/echart/echart.theme.js
uiwiz/elements/echart/themes.py
uiwiz-0.2.5.dist-info/licenses/LICENSE
uiwiz-0.2.5.dist-info/METADATA
uiwiz-0.2.5.dist-info/WHEEL
uiwiz-0.2.5.dist-info/top_level.txt
uiwiz-0.2.5.dist-info/RECORD
