Metadata-Version: 2.4
Name: uiwiz
Version: 0.2.5
Summary: UiWiz is a framework to develop web applications
Requires-Python: >=3.9
License-File: LICENSE
Requires-Dist: fastapi>=0.115.1
Requires-Dist: markdown2[all]>=2.5.3
Requires-Dist: openpyxl>=3.1.5
Requires-Dist: pandas>=2.2.3
Requires-Dist: pyhumps>=3.8.0
Requires-Dist: python-multipart>=0.0.20
Requires-Dist: starlette-authlib>=0.3.12
Requires-Dist: uvicorn[standard]>=0.12.0
Dynamic: license-file
